job_server/__init__.py
job_server/agent_api.py
job_server/agent_worker.py
job_server/config.py
job_server/db.py
job_server/job_api.py
job_server/job_queue.py
job_server/main.py
job_server/models.py
job_server/monitoring.py
job_server/scheduler.py
job_server/schemas.py
qgjob/__init__.py
qgjob/__main__.py
qgjob/cli.py
qgjob/client.py
qgjob/config.py
qgjob/models.py
venv/Lib/site-packages/pip/_internal/operations/build/__init__.py
venv/Lib/site-packages/pip/_internal/operations/build/metadata.py
venv/Lib/site-packages/pip/_internal/operations/build/metadata_editable.py
venv/Lib/site-packages/pip/_internal/operations/build/metadata_legacy.py
venv/Lib/site-packages/pip/_internal/operations/build/wheel.py
venv/Lib/site-packages/pip/_internal/operations/build/wheel_editable.py
venv/Lib/site-packages/pip/_internal/operations/build/wheel_legacy.py
qgjob-1.4.0.dist-info/METADATA
qgjob-1.4.0.dist-info/WHEEL
qgjob-1.4.0.dist-info/entry_points.txt
qgjob-1.4.0.dist-info/top_level.txt
qgjob-1.4.0.dist-info/RECORD
