Metadata-Version: 2.4
Name: qgjob
Version: 1.4.0
Summary: CLI for submitting and tracking AppWright test jobs
License: MIT
Requires-Python: >=3.7
Requires-Dist: typer[all]
Requires-Dist: requests
Requires-Dist: pydantic
